e4stream/__init__.py
e4stream/client.py
e4stream-0.1.1.dist-info/LICENSE
e4stream-0.1.1.dist-info/WHEEL
e4stream-0.1.1.dist-info/METADATA
e4stream-0.1.1.dist-info/RECORD
