Metadata-Version: 2.1
Name: e4stream
Version: 0.1.1
Summary: Python package that provides a simple API for interacting with packets coming from the Empatica E4 Streaming Server
Home-page: https://github.com/jasondraether/e4stream
License: MIT
Keywords: e4,empatica,hubbs
Author: Jason Raether
Author-email: jasondraether@gmail.com
Requires-Python: >=3.9,<4.0
Classifier: License :: OSI Approved :: MIT License
Classifier: Programming Language :: Python :: 3
Classifier: Programming Language :: Python :: 3.10
Classifier: Programming Language :: Python :: 3.9
Project-URL: Repository, https://github.com/jasondraether/e4stream
